sunpeek/__init__.py
sunpeek/api/__init__.py
sunpeek/api/dependencies.py
sunpeek/api/main.py
sunpeek/api/routers/__init__.py
sunpeek/api/routers/api_jobs.py
sunpeek/api/routers/config.py
sunpeek/api/routers/evaluations.py
sunpeek/api/routers/files.py
sunpeek/api/routers/helper.py
sunpeek/api/routers/plant.py
sunpeek/base_model.py
sunpeek/common/__init__.py
sunpeek/common/common_units.py
sunpeek/common/config_parser.py
sunpeek/common/errors.py
sunpeek/common/plot_utils.py
sunpeek/common/time_zone.py
sunpeek/common/unit_uncertainty.py
sunpeek/common/utils.py
sunpeek/components/__init__.py
sunpeek/components/base.py
sunpeek/components/components_factories.py
sunpeek/components/fluids.py
sunpeek/components/fluids_wpd_models.py
sunpeek/components/helpers.py
sunpeek/components/iam_methods.py
sunpeek/components/jobs.py
sunpeek/components/operational_events.py
sunpeek/components/outputs_power_check.py
sunpeek/components/physical.py
sunpeek/components/sensor.py
sunpeek/components/sensor_types.py
sunpeek/components/types.py
sunpeek/core_methods/__init__.py
sunpeek/core_methods/common/__init__.py
sunpeek/core_methods/common/main.py
sunpeek/core_methods/common/shading.py
sunpeek/core_methods/power_check/__init__.py
sunpeek/core_methods/power_check/formula.py
sunpeek/core_methods/power_check/main.py
sunpeek/core_methods/power_check/plotting.py
sunpeek/core_methods/power_check/wrapper.py
sunpeek/core_methods/virtuals/__init__.py
sunpeek/core_methods/virtuals/calculations.py
sunpeek/core_methods/virtuals/main.py
sunpeek/core_methods/virtuals/radiation.py
sunpeek/core_methods/virtuals/virtuals_array.py
sunpeek/core_methods/virtuals/virtuals_plant.py
sunpeek/data_handling/__init__.py
sunpeek/data_handling/context.py
sunpeek/data_handling/data_uploader.py
sunpeek/data_handling/wrapper.py
sunpeek/db_utils/__init__.py
sunpeek/db_utils/crud.py
sunpeek/db_utils/db_data_operations.py
sunpeek/db_utils/init_db.py
sunpeek/definitions/__init__.py
sunpeek/definitions/collectors.py
sunpeek-0.7.3.dist-info/METADATA
sunpeek-0.7.3.dist-info/WHEEL
sunpeek-0.7.3.dist-info/licenses/COPYING
sunpeek-0.7.3.dist-info/licenses/COPYING.LESSER
sunpeek-0.7.3.dist-info/RECORD
