Metadata-Version: 2.4
Name: sunpeek
Version: 0.7.3
Summary: Large Solar Thermal Monitoring Tool. Implements the Power Check Method of ISO 24194
License-Expression: LGPL-3.0-only
License-File: COPYING
License-File: COPYING.LESSER
Keywords: solarthermal,solar,energy,monitoring
Author: Philip Ohnewein, Daniel Tschopp, Lukas Emberger, Marnoch Hamilton-Jones, Jonathan Cazco, Peter Zauner
Maintainer: Marnoch Hamilton-Jones
Maintainer-email: m.hamilton-jones@sunpeek.org
Requires-Python: >=3.11, <3.14
Classifier: Development Status :: 4 - Beta
Classifier: Programming Language :: Python :: 3
Classifier: Programming Language :: Python :: 3.11
Classifier: Programming Language :: Python :: 3.12
Classifier: Programming Language :: Python :: 3.13
Classifier: Topic :: Scientific/Engineering
Provides-Extra: all
Provides-Extra: api
Provides-Extra: db
Provides-Extra: demo
Requires-Dist: alembic ; extra == "all"
Requires-Dist: alembic ; extra == "db"
Requires-Dist: coolprop
Requires-Dist: ephem
Requires-Dist: fastapi (>=0.92) ; extra == "all"
Requires-Dist: fastapi (>=0.92) ; extra == "api"
Requires-Dist: httpx ; extra == "all"
Requires-Dist: httpx ; extra == "api"
Requires-Dist: lxml
Requires-Dist: matplotlib (>=3.7)
Requires-Dist: metpy
Requires-Dist: numpy (>=2)
Requires-Dist: orjson
Requires-Dist: pandas (>=2)
Requires-Dist: parquet-datastore-utils (>=0.1.14)
Requires-Dist: pendulum (>=3.0.0)
Requires-Dist: pint (>=0.22)
Requires-Dist: pint-pandas (>=0.2)
Requires-Dist: protobuf
Requires-Dist: psycopg[binary] (>=3) ; extra == "all"
Requires-Dist: psycopg[binary] (>=3) ; extra == "api"
Requires-Dist: psycopg[binary] (>=3) ; extra == "db"
Requires-Dist: pvlib
Requires-Dist: pydantic (>=2)
Requires-Dist: pypdf (>=6)
Requires-Dist: pyperclip (>=1.8.2)
Requires-Dist: pyproj
Requires-Dist: python-dotenv
Requires-Dist: python-multipart ; extra == "all"
Requires-Dist: python-multipart ; extra == "api"
Requires-Dist: scikit-learn
Requires-Dist: scipy (>=1.16)
Requires-Dist: sqlalchemy (>=2)
Requires-Dist: sqlalchemy-utils
Requires-Dist: statsmodels
Requires-Dist: sunpeek-exampledata ; extra == "all"
Requires-Dist: sunpeek-exampledata ; extra == "demo"
Requires-Dist: timezonefinder (>=8)
Requires-Dist: trio
Requires-Dist: uvicorn[standard] ; extra == "all"
Requires-Dist: uvicorn[standard] ; extra == "api"
Requires-Dist: yamlloader
Project-URL: Documentation, https://docs.sunpeek.org
Project-URL: Repository, https://gitlab.com/sunpeek/sunpeek
